onnxdoctor/__init__.py
onnxdoctor/_checker.py
onnxdoctor/_diagnostics.py
onnxdoctor/_message.py
onnxdoctor/chronology/__init__.py
onnxdoctor/chronology/_snapshot.py
onnxdoctor/diagnostics_providers/__init__.py
onnxdoctor/diagnostics_providers/sparsity.py
onnxdoctor/diagnostics_providers/sparsity_test.py
onnxdoctor/diagnostics_providers/onnxruntime_compatibility/__init__.py
onnx_doctor-0.0.2.dist-info/LICENSE
onnx_doctor-0.0.2.dist-info/METADATA
onnx_doctor-0.0.2.dist-info/WHEEL
onnx_doctor-0.0.2.dist-info/top_level.txt
onnx_doctor-0.0.2.dist-info/RECORD
