Metadata-Version: 2.1
Name: onnx-doctor
Version: 0.0.2
Summary: Extensible and beautiful ONNX checker
Author-email: Justin Chu <justinchuby@users.noreply.github.com>
License: MIT License
Project-URL: Documentation, https://github.com/justinchuby/onnx-doctor#readme
Project-URL: Issues, https://github.com/justinchuby/onnx-doctor/issues
Project-URL: Source, https://github.com/justinchuby/onnx-doctor
Classifier: Development Status :: 3 - Alpha
Classifier: Environment :: Console
Classifier: Intended Audience :: Developers
Classifier: Operating System :: POSIX
Classifier: Operating System :: MacOS :: MacOS X
Classifier: Operating System :: Microsoft :: Windows
Classifier: Programming Language :: Python :: 3.8
Classifier: Programming Language :: Python :: 3.9
Classifier: Programming Language :: Python :: 3.10
Classifier: Programming Language :: Python :: 3.11
Classifier: Programming Language :: Python :: 3.12
Classifier: License :: OSI Approved :: MIT License
Requires-Python: >=3.8
License-File: LICENSE
Requires-Dist: onnx >=1.16
Requires-Dist: onnxscript
Requires-Dist: rich
